cosmodiscovery/__init__.py
cosmodiscovery/client.py
cosmodiscovery/message.py
cosmodiscovery/server.py
cosmodiscovery/utils.py
cosmodiscovery-0.1.0.dist-info/LICENSE
cosmodiscovery-0.1.0.dist-info/METADATA
cosmodiscovery-0.1.0.dist-info/WHEEL
cosmodiscovery-0.1.0.dist-info/top_level.txt
cosmodiscovery-0.1.0.dist-info/RECORD
