Metadata-Version: 2.1
Name: cosmodiscovery
Version: 0.1.0
Summary: A Free Network Discovery Service
Home-page: https://github.com/SamHDev/CosmoDiscovery/
Author: SamHDev
Author-email: sam02h.huddart@gmail.com
License: UNKNOWN
Platform: UNKNOWN
Classifier: Programming Language :: Python :: 3
Classifier: Operating System :: OS Independent
